dictionary_profanity_filter/__init__.py
dictionary_profanity_filter/__main__.py
dictionary_profanity_filter/profanity_filter.py
dictionary_profanity_filter/data/default_list.txt
tests/__init__.py
tests/test_profanity_filter.py
dictionary_profanity_filter-1.0.4.dist-info/LICENSE
dictionary_profanity_filter-1.0.4.dist-info/METADATA
dictionary_profanity_filter-1.0.4.dist-info/WHEEL
dictionary_profanity_filter-1.0.4.dist-info/entry_points.txt
dictionary_profanity_filter-1.0.4.dist-info/top_level.txt
dictionary_profanity_filter-1.0.4.dist-info/RECORD
