Metadata-Version: 2.1
Name: dictionary-profanity-filter
Version: 1.0.4
Summary: Python profanity filter
Home-page: https://github.com/ProgrammingLanguageLeader/dictionary-profanity-filter
Author: Dmitry Shorokhov
Author-email: vip.shoroch@gmail.com
License: MIT license
Platform: UNKNOWN
Classifier: Programming Language :: Python :: 3
Classifier: License :: OSI Approved :: MIT License
Classifier: Operating System :: OS Independent
Classifier: Topic :: Software Development :: Libraries :: Python Modules
Requires-Dist: DAWG-Python (==0.7.2)
Requires-Dist: alphabet-detector (==0.0.7)
Requires-Dist: docopt (==0.6.2)
Requires-Dist: inflection (==0.3.1)
Requires-Dist: pymorphy2-dicts (==2.4.393442.3710985)
Requires-Dist: pymorphy2 (==0.8)
